[
  {
    "name": "gold_50",
    "type": "text",
    "roi": "428,120,338,389",
    "area": "0,0,100,100",
    "keyword": "战斗胜利获得的金币增加50%",
    "description": "Ocr-description"
  },
  {
    "name": "gold_100",
    "type": "text",
    "roi": "425,118,342,397",
    "area": "0,0,100,100",
    "keyword": "战斗胜利获得的金币增加100%",
    "description": "Ocr-description"
  },
  {
    "name": "exp_50",
    "type": "text",
    "roi": "426,119,335,394",
    "area": "0,0,100,100",
    "keyword": "战斗胜利获得的经验增加50%",
    "description": "Ocr-description"
  },
  {
    "name": "exp_100",
    "type": "text",
    "roi": "421,127,342,388",
    "area": "0,0,100,100",
    "keyword": "战斗胜利获得的经验增加100%",
    "description": "Ocr-description"
  }
]